topsis/__init__.py
topsis/topsis.py
topsis_102203733-0.0.1.dist-info/LICENSE
topsis_102203733-0.0.1.dist-info/METADATA
topsis_102203733-0.0.1.dist-info/WHEEL
topsis_102203733-0.0.1.dist-info/entry_points.txt
topsis_102203733-0.0.1.dist-info/top_level.txt
topsis_102203733-0.0.1.dist-info/RECORD
