Metadata-Version: 2.1
Name: topsis_102203733
Version: 0.0.1
Summary: Technique for Order Preference by Similarity to Ideal Solution(TOPSIS) Package
Author: Akshit Kumar Markan
Author-email: akmarkan28@gmail.com
Keywords: python,topsis,multi-criteria decision-making,mcdm,ranking
Classifier: Programming Language :: Python :: 3
Classifier: License :: OSI Approved :: MIT License
Classifier: Operating System :: OS Independent
Requires-Python: >=3.6
License-File: LICENSE
Requires-Dist: numpy
Requires-Dist: pandas
Requires-Dist: openpyxl
